enumchecker.py
enumchecker-1.0.0.dist-info/LICENSE
enumchecker-1.0.0.dist-info/METADATA
enumchecker-1.0.0.dist-info/WHEEL
enumchecker-1.0.0.dist-info/entry_points.txt
enumchecker-1.0.0.dist-info/top_level.txt
enumchecker-1.0.0.dist-info/RECORD
