Metadata-Version: 2.1
Name: enumchecker
Version: 1.0.0
Summary: Checks your python enums. Eliminates common errors.
Home-page: UNKNOWN
Author: Suade Labs
Author-email: UNKNOWN
License: UNKNOWN
Platform: UNKNOWN
Classifier: Topic :: Software Development :: Testing
